proxyfox/__init__.py
proxyfox/proxyfox.py
proxyfox-0.2.0.dist-info/licenses/LICENSE
proxyfox-0.2.0.dist-info/METADATA
proxyfox-0.2.0.dist-info/WHEEL
proxyfox-0.2.0.dist-info/top_level.txt
proxyfox-0.2.0.dist-info/RECORD
