Metadata-Version: 2.4
Name: proxyfox
Version: 0.2.0
Summary: A simple Python package to fetch working proxies with filtering capabilities
Home-page: https://github.com/redmoon0x/proxyfox
Author: Dev shetty
Author-email: deviprasadshetty400@gmail.com
Project-URL: Bug Reports, https://github.com/redmoon0x/proxyfox/issues
Project-URL: Source, https://github.com/redmoon0x/proxyfox
Keywords: proxy,proxies,proxy-list,proxy-server,proxy-checker
Classifier: Development Status :: 4 - Beta
Classifier: Intended Audience :: Developers
Classifier: License :: OSI Approved :: MIT License
Classifier: Operating System :: OS Independent
Classifier: Programming Language :: Python :: 3
Classifier: Programming Language :: Python :: 3.6
Classifier: Programming Language :: Python :: 3.7
Classifier: Programming Language :: Python :: 3.8
Classifier: Programming Language :: Python :: 3.9
Classifier: Topic :: Internet :: Proxy Servers
Classifier: Topic :: Software Development :: Libraries :: Python Modules
Requires-Python: >=3.6
License-File: LICENSE
Requires-Dist: requests>=2.25.0
Dynamic: author
Dynamic: author-email
Dynamic: classifier
Dynamic: description
Dynamic: description-content-type
Dynamic: home-page
Dynamic: keywords
Dynamic: license-file
Dynamic: project-url
Dynamic: requires-dist
Dynamic: requires-python
Dynamic: summary
